kitti_iterator/__init__.py
kitti_iterator/ground_removal.py
kitti_iterator/helper.py
kitti_iterator/kitti_raw_iterator.py
kitti_iterator/plotter.py
KITTI_Iterator-1.4.0.dist-info/METADATA
KITTI_Iterator-1.4.0.dist-info/WHEEL
KITTI_Iterator-1.4.0.dist-info/top_level.txt
KITTI_Iterator-1.4.0.dist-info/RECORD
