Metadata-Version: 2.1
Name: KITTI-Iterator
Version: 1.4.0
Summary: KITTI Iterator
Home-page: UNKNOWN
License: UNKNOWN
Platform: OS Independent
Requires-Dist: pandas
